tests/audio/__init__.py
tests/audio/file_audio_source_test.py
tests/audio/playlist_test.py
tests/audio/processor_test.py
tests/audio/track_test.py
tests/audio/volatile_audio_test.py
tests/misc/__init__.py
tests/misc/speech_engine_test.py
tests/misc/track_fmt_test.py
tests/view/__init__.py
tests/view/args_test.py
tests/view/config_test.py
tests/view/context_test.py
tests/view/validator_test.py
vxt/__init__.py
vxt/__main__.py
vxt/audio/__init__.py
vxt/audio/audio.py
vxt/audio/audio_source.py
vxt/audio/error.py
vxt/audio/file_audio_source.py
vxt/audio/playlist.py
vxt/audio/processor.py
vxt/audio/speaker.py
vxt/audio/track.py
vxt/audio/volatile_audio.py
vxt/misc/__init__.py
vxt/misc/speech_engine.py
vxt/misc/track_fmt.py
vxt/speech2text/__init__.py
vxt/speech2text/bing.py
vxt/speech2text/engine.py
vxt/speech2text/google.py
vxt/speech2text/google_cloud.py
vxt/speech2text/houndify.py
vxt/speech2text/ibm.py
vxt/speech2text/sphinx.py
vxt/view/__init__.py
vxt/view/args.py
vxt/view/config.py
vxt/view/context.py
vxt/view/helper.py
vxt/view/validator.py
vxt/view/view.py
vxt/view/task/__init__.py
vxt/view/task/factory.py
vxt/view/task/task.py
vxt/view/task/audio/__init__.py
vxt/view/task/audio/amplify.py
vxt/view/task/audio/delete_track.py
vxt/view/task/audio/export.py
vxt/view/task/audio/normalize.py
vxt/view/task/audio/play.py
vxt/view/task/audio/rename_track.py
vxt/view/task/audio/split_silence.py
vxt/view/task/audio/split_track.py
vxt/view/task/misc/__init__.py
vxt/view/task/speech2text/__init__.py
vxt/view/task/speech2text/manual.py
vxt/view/task/speech2text/speech.py
vxt-0.1.2.dist-info/LICENSE
vxt-0.1.2.dist-info/METADATA
vxt-0.1.2.dist-info/WHEEL
vxt-0.1.2.dist-info/entry_points.txt
vxt-0.1.2.dist-info/top_level.txt
vxt-0.1.2.dist-info/RECORD
