Metadata-Version: 2.1
Name: vxt
Version: 0.1.2
Summary: A python CLI tool to extract voice sentences from audio files with speech recognition
Home-page: https://github.com/veeso/vxt
Author: Christian Visintin
Author-email: christian.visintin1997@gmail.com
License: MIT
Keywords: Speech recognition,voice extract,audio voice,split audio
Classifier: Development Status :: 5 - Production/Stable
Classifier: Intended Audience :: Developers
Classifier: Intended Audience :: End Users/Desktop
Classifier: License :: OSI Approved :: MIT License
Classifier: Programming Language :: Python :: 3
Classifier: Operating System :: OS Independent
Classifier: Programming Language :: Python :: 3
Classifier: Programming Language :: Python :: 3.8
Requires-Python: >=3.8
License-File: LICENSE
Requires-Dist: click (>=8)
Requires-Dist: pathlib2 (>=2)
Requires-Dist: inquirer (>=2.8)
Requires-Dist: pydub (>=0.25)
Requires-Dist: PyInquirer (>=1.0.3)
Requires-Dist: SpeechRecognition (>=3.8)
Requires-Dist: termcolor (>=1)
Requires-Dist: yaspin (>=2)
